README.md
setup.py
quina/__init__.py
quina.egg-info/PKG-INFO
quina.egg-info/SOURCES.txt
quina.egg-info/dependency_links.txt
quina.egg-info/requires.txt
quina.egg-info/top_level.txt
quina/core/__init__.py
quina/core/event_loop.py
quina/core/point.py
quina/core/qt_app.py
quina/core/rect.py
quina/core/signal_sender.py
quina/core/size.py
quina/core/timer.py
quina/gui/__init__.py
quina/gui/painter.py
quina/gui/pen.py
quina/gui/utils.py
quina/model/__init__.py
quina/model/base.py
quina/model/project.py
quina/model/widget_types.py
quina/model/types/__init__.py
quina/model/types/dict_type.py
quina/model/types/float_type.py
quina/model/types/integer_type.py
quina/model/types/list_type.py
quina/model/types/string_list_type.py
quina/model/types/string_type.py
quina/model/types/time_point_type.py
quina/widgets/__init__.py
quina/widgets/interfaces/__init__.py
quina/widgets/interfaces/class_exec_interface.py
quina/widgets/interfaces/closed_signal_interface.py
quina/widgets/interfaces/excited_signal_interface.py
quina/widgets/interfaces/message_box_interface.py
quina/widgets/layouts/__init__.py
quina/widgets/layouts/square_layout.py
quina/widgets/widgets/__init__.py
quina/widgets/widgets/action.py
quina/widgets/widgets/base_widget.py
quina/widgets/widgets/combo_box.py
quina/widgets/widgets/date_edit.py
quina/widgets/widgets/dialog.py
quina/widgets/widgets/dock_widget.py
quina/widgets/widgets/double_spin_box.py
quina/widgets/widgets/group_box.py
quina/widgets/widgets/input_dialog.py
quina/widgets/widgets/label.py
quina/widgets/widgets/line_edit.py
quina/widgets/widgets/list_widget.py
quina/widgets/widgets/main_window.py
quina/widgets/widgets/push_button.py
quina/widgets/widgets/shortcut.py
quina/widgets/widgets/spin_box.py
quina/widgets/widgets/table_widget.py
quina/widgets/widgets/widget.py