Metadata-Version: 2.1
Name: quina
Version: 0.1.6
Summary: PySide2 MVVM Framework
Home-page: https://github.com/KD-Group/quina
Author: KD-Group
Author-email: sfzhou.scut@gmail.com
License: GPL-3.0
Keywords: PySide2 MVVM
Platform: UNKNOWN
Classifier: Development Status :: 3 - Alpha
Classifier: Intended Audience :: Developers
Classifier: Programming Language :: Python :: 3
Provides-Extra: test
